maskay/__init__.py
maskay/module.py
maskay/predict.py
maskay/tensorflow.py
maskay/tensorsat.py
maskay/torch.py
maskay/utils.py
maskay/download/__init__.py
maskay/download/s2/__init__.py
maskay/download/s2/pc.py
maskay/download/s2/safe.py
maskay/download/s2/safegee.py
maskay/library/CDFCNNrgbi.py
maskay/library/CDFCNNrgbiswir.py
maskay/library/KappaMaskL1C.py
maskay/library/KappaMaskL2A.py
maskay/library/__init__.py
maskay/library/dynamicworld.py
maskay/library/unetmobv2.py
maskay-0.0.1.8.dist-info/LICENSE
maskay-0.0.1.8.dist-info/METADATA
maskay-0.0.1.8.dist-info/WHEEL
maskay-0.0.1.8.dist-info/top_level.txt
maskay-0.0.1.8.dist-info/RECORD
