Metadata-Version: 2.1
Name: maskay
Version: 0.0.1.8
Summary: A Python package for cloud masking in Sentinel 2
Home-page: https://github.com/cloudsen12/maskay
Author: David Montero Loaiza
Author-email: dml.mont@gmail.com
License: MIT
Classifier: Development Status :: 2 - Pre-Alpha
Classifier: License :: OSI Approved :: MIT License
Classifier: Programming Language :: Python
Classifier: Programming Language :: Python :: 3.6
Classifier: Programming Language :: Python :: 3.7
Classifier: Programming Language :: Python :: 3.8
Classifier: Programming Language :: Python :: 3.9
License-File: LICENSE
Requires-Dist: rioxarray
Requires-Dist: requests
Requires-Dist: gdown
Requires-Dist: numpy
